{"cameraMode":{"drawMode":0,"name":"Shaded","section":"Shading Mode"},"sceneLighting":false,"audioPlay":false,"sceneViewState":{"m_AlwaysRefresh":false,"showFog":true,"showSkybox":false,"showFlares":true,"showImageEffects":true,"showParticleSystems":true,"showVisualEffectGraphs":true,"m_FxEnabled":true},"in2DMode":false,"pivot":{"x":100.03018188476563,"y":90.60781860351563,"z":-229.72760009765626},"rotation":{"x":0.17977437376976014,"y":-0.4660578668117523,"z":0.0971565991640091,"w":0.860758900642395},"size":2.075819730758667,"orthographic":false}